deckocards/__init__.py
deckocards/card.py
deckocards/deck.py
deckocards-0.0.1.dist-info/LICENSE.md
deckocards-0.0.1.dist-info/METADATA
deckocards-0.0.1.dist-info/WHEEL
deckocards-0.0.1.dist-info/top_level.txt
deckocards-0.0.1.dist-info/RECORD
