Metadata-Version: 2.1
Name: deckocards
Version: 0.0.1
Summary: Allows you to play with card decks
Home-page: UNKNOWN
Author: Arnold Johnson
Author-email: randomnest74@gmail.com
License: UNKNOWN
Platform: UNKNOWN
Classifier: Programming Language :: Python :: 3
Classifier: License :: OSI Approved :: MIT License
Classifier: Operating System :: OS Independent
Requires-Python: >=3
